sleazy/__about__.py
sleazy/__init__.py
sleazy-0.2.0.dist-info/METADATA
sleazy-0.2.0.dist-info/WHEEL
sleazy-0.2.0.dist-info/RECORD
