Metadata-Version: 2.4
Name: sleazy
Version: 0.2.0
Summary: TypedDict based cli argument parsing
Author-email: Robin van der Noord <robinvandernoord@gmail.com>
Requires-Python: >=3.12
Provides-Extra: dev
Requires-Dist: pytest; extra == 'dev'
Requires-Dist: pytest-cov; extra == 'dev'
